{
  "id": "0822a1ee",
  "title": "Data Scientist - 90394595 - Washington",
  "company": "Amtrak",
  "url": "https://www.indeed.com/viewjob?jk=109c7e60368536ef",
  "source": "jobspy_indeed",
  "intake_source": "api",
  "raw_jd": "**\\*\\*\\*\\*PLEASE NOTE: \\*\\*\\*\\***\n\n**Amtrak OIG is not a Federal agency. Our employment opportunities are not federal jobs.**\n\n **\\*\\*\\*This position requires U.S. citizenship or lawful permanent resident status. The OIG does not sponsor work visas or provide employment\\-based immigration sponsorship of any kind.\\*\\*\\***\n\n  \n\nJoin with the Inspector General to help make America\u2019s railroad operate more efficiently and effectively. Our team provides independent oversight of Amtrak\u2019s programs and operations and works diligently to prevent and detect fraud, waste, and abuse by Amtrak employees, contractors, or vendors. This work not only helps to improve the efficiency and effectiveness of Amtrak, but it also informs decision\\-making by Amtrak\u2019s Board of Directors, Amtrak management, and Congress. We employ a diverse team of auditors, special agents, analysts, forensic examiners, lawyers, and support staff to complete our exciting mission. Join us as we continue toward our goal of building a model OIG centered on independence, teamwork, diversity, work\\-life balance, and oversight that makes a difference!\n\n **SUMMARY OF DUTIES**\n\n  \n\nThe Data Scientist collects, prepares and analyzes data to help the OIG conduct audits and investigations of Amtrak (the company) programs and operations, in accordance with lawful standards. The incumbent will support complex audits and sensitive criminal, civil, and administrative investigations with data analytics strategies that help assess the economy, efficiency, and effectiveness of Amtrak programs and operations and help identify potential fraud, waste, and abuse. Evidence the incumbent develops may also be used by OIG investigators for civil or criminal accountability in conjunction with relevant United States Attorney Offices. The incumbent will work with OIG Data Analysts, Data Engineers, and company resources to access data, learn related business processes, identify relevant internal controls, ensure completeness and accuracy of the data, and generate business insights using advanced data analytics techniques such as machine learning and artificial intelligence.\n\n **ESSENTIAL FUNCTIONS**\n\n  \n\nCentral Function for Oversight Analytics\n\n  \n\n* Serves as a subject\u2011matter expert on data science, advanced analytics, fraud detection, and quantitative risk assessment.\n* Advances the strategic vision for audit and investigative analytics across the OIG.\n* Takes direction from the Director and Senior Director of Data Analytics to prioritize analytic efforts but works independently without significant supervisory guidance in collecting, preparing, and analyzing data.\n* Follows best practices and/or established analytic standards, methodologies, quality control practices to ensure compliance with OIG and company policies.\n* Become an expert in using Alteryx as a primary tool for building analytic tests.\n\n  \n\nFraud, Waste \\& Abuse Detection\n\n  \n\n* Designs, develops, and oversees advanced data analytics tests, statistical models, and machine learning solutions to detect potential fraud, waste, abuse, and improper payments.\n* Builds risk\u2011scoring and prioritization frameworks to support audit planning and investigative targeting.\n\n  \n\nInternal Control \\& Risk Analytics\n\n  \n\n* Learns company systems and business processes and identifies internal controls relevant to analytic objectives.\n* Conducts data\u2011driven assessments of internal control effectiveness by identifying systemic control weaknesses, compliance risks, and process inefficiencies across program areas.\n\n  \n\nData Collection and Management\n\n  \n\n* Designs and implements automated data extraction, transformation, and loading (ETL) routines for complex and large datasets from internal and external systems.\n* Monitors changes to source systems that affect data integrity, access, or analytics outputs.\n* Independently prepares, cleans, normalizes, and validates data to ensure data integrity, completeness, and reliability prior to analytical use.\n* Performs quality assurance reviews of others\u2019 work and prepares own reports to a high degree of excellence.\n* Meets with the company officials to obtain an accurate understanding of systems, business processes, and related data structures, for the purpose of informing analytical work.\n\n  \n\nOversight Engagement Support\n\n  \n\n* Works with auditors and investigators to understand objectives, identify relevant data, brainstorm analytic approaches, and interpret results.\n* Proposes expert analytic strategies using available tools to identify trends, anomalies, relationships, and patterns across large and complex datasets.\n* Ensures analytic evidence is reliable, sufficient, relevant, and defensible for audit findings or investigative use.\n\n  \n\nCommunication, Visualization \\& Reporting\n\n  \n\n* Creates advanced visualizations, dashboards, exhibits, and automated reports that provide business insights and illustrate risk areas for audits and investigations.\n* Prepares briefing materials, testimony, messages, and fact sheets that clearly and effectively communicate analytic methods and results to technical and non\u2011technical stakeholders.\n* Assists the Office of Counsel in litigation preparation and testifies as a data analytics expert when required.\n\n  \n\nCollaboration, Governance \\& Security\n\n  \n\n* Develops productive working relationships with internal and external stakeholders at all organizational levels.\n* Meets regularly with the team to discuss progress and obstacles and recommend solutions. Ensures work, information, ideas, and technology flow freely.\n* Works with Data Engineers and OIG IT Mission Support to implement data governance, security, and access controls.\n\n **MINIMUM REQUIREMENTS:**\n\n  \n\n* Bachelor\u2019s degree in Data Science, Statistics, Computer Science, Information Systems, or related quantitative field.\n* 5\\+ years of progressive experience performing advanced data analytics in audit, investigation, fraud detection, or compliance environments.\n* Expert proficiency with Python, R, SQL, Power BI, Alteryx, ACL, and cloud\u2011based analytics platforms.\n* 3\\+ years of experience developing analytical solutions using cloud native tools and APIs for ETL, storage, and analysis.\n\n **PREFERRED:**\n\n  \n\n* Master\u2019s degree in Data Science, Data Analytics, Statistics, Computer Science, Information Systems, or other fields related to data analysis, machine learning, artificial intelligence, business information management, or forensic accounting.\n* Professional certifications such as CFE, CIA, CISA, or equivalent.\n* Advanced proficiency performing statistical analysis using data analytics software packages, or cloud native tools.\n* Strong analytic skills related to working with unstructured datasets.\n* Knowledge of working with JSON format data, including parsing and stringifying.\n* Experience designing and implementing Artificial Intelligence strategy.\n* Experience presenting analytic evidence in criminal, civil, or administrative proceedings.\n* Investigative experience with an emphasis on complex white\\-collar crimes involving contracts, procurement, vendors, finance, human resources, public corruption, revenue, and health care.\n* Broad knowledge of the laws, practices, and procedures of federal Offices of Inspector General.\n* Familiarity with passenger rail or transportation operations\n\n **COMPENSATION:**\n\n  \n\nThe hiring salary range for the Data Scientist is $124,600 \\- $160,500\\. This is the starting salary range and does not reflect the full salary range of the position. Pay is based on several factors including but not limited to education, work experience, certifications, internal equity, etc. In addition to your salary, Amtrak OIG offers a comprehensive benefit package that includes health, dental, and vision plans; health savings accounts; wellness programs; flexible spending accounts; 401K retirement plan with employer match; life insurance; short and long term disability insurance; paid time off; back\\-up care; adoption assistance; surrogacy assistance; reimbursement of education expenses; Public Service Loan Forgiveness eligibility; Railroad Retirement sickness and retirement benefits; and rail pass privileges. Learn more about our benefits offerings here.\n\n  \n\nRequisition ID: 166329  \n\nBand Zone: D1C\n\n\nLocation: Washington D.C.\n\n\nWork Arrangement: Onsite\n\n\nRelocation: No\n\n\nTravel: Yes \u2013 25%\n\n  \n\nYou power our progress through your performance.\n\n  \n\nWe want your work at Amtrak to be more than a job. We want your career at Amtrak to be a fulfilling experience where you find challenging work, rewarding opportunities, respect among colleagues, and attractive compensation. Amtrak maintains a culture that values high performance and recognizes individual employee contributions.\n\n  \n\nAmtrak is committed to a safe workplace free of drugs and alcohol. All Amtrak positions requires a pre\\-employment background check that includes prior employment verification, a criminal history check and a pre\\-employment drug screen.\n\n\nCandidates who test positive for marijuana will be disqualified, regardless of any state or local statute, ordinance, regulation, or other law that legalizes or decriminalizes the use or possession of marijuana, whether for medical, recreational, or other use. Amtrak's pre\\-employment drug testing program is administered in accordance with DOT regulations and applicable law.\n\n  \n\nIn accordance with DOT regulations (49 CFR \u00a7 40\\.25\\), Amtrak is required to obtain prior drug and alcohol testing records for applicants/employees intending to perform safety\\-sensitive duties for covered Department of Transportation positions. If an applicant/employee refuses to provide written consent for Amtrak to obtain these records, the individual will not be permitted to perform safety\\-sensitive functions.\n\n  \n\nIn accordance with federal law governing security checks of covered individuals for providers of public transportation (Title 6 U.S.C. \u00a71143\\), Amtrak is required to screen applicants for any permanent or interim disqualifying criminal offenses.\n\n  \n\nNote that any education requirement listed above may be deemed satisfied if you have an equivalent combination of education, training and experience.\n\n  \n\nAmtrak is an equal opportunity employer and all qualified applicants will receive consideration for employment without regard to race/color, to include traits historically associated with race, including but not limited to, hair texture and hairstyles such as braids, locks and twists, religion, sex (including pregnancy, childbirth and related conditions, such as lactation), national origin/ethnicity, disability (intellectual, mental and physical), veteran status, marital status, ancestry, sexual orientation, gender identity and gender expression, genetic information, citizenship or any other personal characteristics protected by law.",
  "pay_range": "$124,600 - $160,500/year",
  "market_lane": "w2_sniper",
  "status": "scored",
  "score": {
    "skills_match": 4,
    "scope_impact": 3,
    "pay_alignment": 1,
    "gut_interest": 0,
    "total": 8,
    "skills_rationale": "Perfect technical skills alignment with Python, R, SQL, Power BI, ETL/data pipelines, and cloud analytics platforms. The role requires advanced data analytics, fraud detection, and ML/AI work that directly matches candidate's expertise in data science, BI architecture, and analytics delivery.",
    "scope_rationale": "Excellent scope match for a senior individual contributor role requiring independent work, subject matter expertise, and strategic analytics leadership. The position involves leading complex analytics initiatives, working with executives, and serving as a technical expert - all consistent with candidate's senior architect background.",
    "pay_rationale": "The salary range of $124,600-$160,500 is at the lower end of candidate's W2 target range ($160,000-$220,000), making this a borderline pay fit.",
    "keyword_gaps": [
      "Alteryx",
      "ACL",
      "CFE certification",
      "forensic accounting"
    ],
    "red_flags": [
      "On-site only in Washington DC",
      "25% travel requirement",
      "Pre-employment drug screening with strict marijuana policy",
      "Requires U.S. citizenship or permanent resident status"
    ],
    "bullshit_flag": false,
    "bullshit_reason": "",
    "recommended_resume": "director",
    "recommended_lane": "w2_sniper",
    "raw_analysis": "This is a high-quality senior data science role with excellent technical alignment for fraud detection and advanced analytics work. The scope perfectly matches the candidate's expertise in BI architecture, data governance, and executive-level analytics delivery. While the pay is at the lower end of target range, the mission-driven work in oversight and investigation could be compelling. The main concerns are the strict on-site requirement and drug testing policies."
  },
  "cover_letters": [],
  "tailored_resume": "",
  "tailored_resume_docx": "",
  "applied_at": "",
  "follow_up": {
    "due_at": "",
    "sent_at": "",
    "count": 0,
    "contact_email": "",
    "contact_name": "",
    "contact_phone": "",
    "extracted_emails": [],
    "extracted_links": [],
    "notes": ""
  },
  "emails": [],
  "notes": "Source: indeed | Posted: 2026-04-08 | Type: nan",
  "created_at": "2026-04-10T15:17:55.502996",
  "updated_at": "2026-04-10T15:18:06.719394",
  "status_history": [
    {
      "from": "new",
      "to": "scored",
      "at": "2026-04-10T15:18:06.719348"
    }
  ]
}