{
  "id": "11bfc85e",
  "title": "Workday Financials Senior Solution Architect/Functional Lead",
  "company": "GEICO",
  "url": "https://www.linkedin.com/jobs/view/4396350740",
  "source": "jobspy_linkedin",
  "intake_source": "api",
  "raw_jd": "GEICO is seeking\n **Finance Data specialists** \n to support the build out of a\n **Finance Data Mart/Lake** \n by partnering with both Finance and Technology teams to redesign the way they use their technologies in managing GEICO's business. This individual must have strong functional and technical Finance Systems background to partner with the Business ensuring effective discussions to drive the capture, transformation, and utilization of Finance data to meet Business goals.\n \n\n\n\n The\n **Staff** \n**Solutions Architect for Finance Data Systems** \n will report to the Senior Director of Finance Technologies will provide solutions on how to build out, maintain, and support a Finance Data repository to support FP\\&A processing and analytics while also supporting the larger Finance organization\u2019s need for Finance data. The Finance Data Systems Solutions Architect will work with multiple Finance and Technology leaders to support the build out the company\u2019s Finance Data Mart/Lake to provide a central repository for all Financial related transactions so it can be a reconciled source of truth for processing and the source for Revenue and Expense analytics. This role is also accountable to support the delivery of technology solutions that will support FP\\&A Planning/Budgeting, financial reporting, Revenue/Expense Analytics, and the build out of the Finance Data Mart to become a reconciled source to allow the GL to become a \u201cthin\u201d ledger.\n \n\n\n\n The ideal candidate has\n **deep Finance Systems experience** \n across multiple companies, a\n **background in ERP and Finance/Data Warehouse** \n from both technical and functional aspects, and has supported the deployment of best practices leveraging their broad knowledge of various\n **ERPs (e.g. PeopleSoft; Oracle EBS; Workday; or SAP** \n ). Prior Financial Services Industry experience is needed to be considered.\n \n\n\n\n**Position Responsibilities** \n\n\n\n\n As a Staff Solutions Architect supporting Finance Data Systems functions you will:\n \n\n\n* Leverage your strong Functional and Technical systems expertise to drive towards the right solution to support the department and GEICO\u2019s current and future needs\n* Engage in cross\\-functional collaboration throughout the entire software lifecycle\n* Support design sessions with peers to ensure systems are well designed, efficient, and meet Business expectations\n* Collaborate with Finance Leaders within the FP\\&A, Controllers, Financial Reporting, and Finance QA \\& Systems team along with the Data Engineering and Finance Technology leaders to ensure organizational goals are met\n* Have a deep understanding of a few Finance functions to support the establishment of a vision and technology roadmap to build out a Finance Data Lake\n* Support the development of a roadmap and then work towards implementing Revenue and Expense Analytical solutions\n* Work with Business leaders to develop project roadmaps which align to business objectives and sequenced by priority and resource availability\n* Support and try to influence customers and stakeholders, and work through divergent expectations\n* Support the implementation of a strong control and governance framework and maintain it for SOX and Audit reviews\n* Support Business and Technology discussions at various levels to ensure alignment towards long term goals of Finance and Technology\n* Analyze and translate business and functional specifications and change requests into technical specifications\n* Share best practices and improve processes within and across teams\n\n\n\n**Qualifications** \n\n\n\n* 15\\+ years of Finance Systems experience with industry leading ERP solutions (e.g. implementing and supporting PeopleSoft; Oracle EBS; Oracle Cloud; Workday; or SAP)\n* 3\\+ years of experience in implementing and supporting FP\\&A applications\n* 3\\+ years working with or supporting a Finance Data Lake/Warehouse/Mart along with various Financial Reporting tools\n* 5\\+ years as a lead supporting Financials via the major vendors (e.g. PeopleSoft; Oracle EBS; Oracle Cloud; Workday; or SAP)\n* Deep Finance domain expertise to be able to work with senior Finance leaders to interpret their process and functional needs into system solutions\n* Strong understanding of FP\\&A Budgeting, Planning, and Reforecasting processes\n* Experience in implementing or supporting Revenue or Expense analytical solutions\n* Good understanding of Accounting process and reporting expectations to partner with Finance teams\n* Ability to communicate and work directly with users across Technology and Finance\n* Sound understanding of project management techniques, methodologies, and best practices\n* Strong problem\\-solving abilities\n* Ability to excel in a fast\\-paced environment\n* Knowledge and experience with the software development life cycle\n* Ability to work independently and in a team\\-oriented collaborative environment\n\n\n\n**Education** \n\n\n\n* Bachelor\u2019s degree in Computer Science, Information Systems, Engineering, Business Administration, or equivalent education or work experience\n\n\n\n**Annual Salary** \n\n\n\n\n $115,000\\.00 \\- $230,000\\.00\n \n\n\n\n The above annual salary range is a general guideline. Multiple factors are taken into consideration to arrive at the final hourly rate/ annual salary to be offered to the selected candidate. Factors include, but are not limited to, the scope and responsibilities of the role, the selected candidate\u2019s work experience, education and training, the work location as well as market and business considerations.\n \n\n\n\n GEICO will consider sponsoring a new qualified applicant for employment authorization for this position.\n \n\n\n\n**Benefits:** \n\n\n\n\n As an Associate, you\u2019ll enjoy our Total Rewards Program\\* to help secure your financial future and preserve your health and well\\-being, including:\n \n\n\n* Premier Medical, Dental and Vision Insurance with no waiting period\\*\\*\n* Paid Vacation, Sick and Parental Leave\n* 401(k) Plan\n* Tuition Reimbursement\n* Paid Training and Licensures\n* Benefits may be different by location. Benefit eligibility requirements vary and may include length of service.\n* Coverage begins on the date of hire. Must enroll in New Hire Benefits within 30 days of the date of hire for coverage to take effect.\n\n\n\n The equal employment opportunity policy of the GEICO Companies provides for a fair and equal employment opportunity for all associates and job applicants regardless of race, color, religious creed, national origin, ancestry, age, gender, pregnancy, sexual orientation, gender identity, marital status, familial status, disability or genetic information, in compliance with applicable federal, state and local law. GEICO hires and promotes individuals solely on the basis of their qualifications for the job to be filled.\n \n\n\n\n GEICO reasonably accommodates qualified individuals with disabilities to enable them to receive equal employment opportunity and/or perform the essential functions of the job, unless the accommodation would impose an undue hardship to the Company. This applies to all applicants and associates. GEICO also provides a work environment in which each associate is able to be productive and work to the best of their ability. We do not condone or tolerate an atmosphere of intimidation or harassment. We expect and require the cooperation of all associates in maintaining an atmosphere free from discrimination and harassment with mutual respect by and for all associates and applicants.",
  "pay_range": "$nan - $nan",
  "market_lane": "contract",
  "status": "new",
  "score": null,
  "cover_letters": [],
  "tailored_resume": "",
  "tailored_resume_docx": "",
  "applied_at": "",
  "follow_up": {
    "due_at": "",
    "sent_at": "",
    "count": 0,
    "contact_email": "",
    "contact_name": "",
    "contact_phone": "",
    "extracted_emails": [],
    "extracted_links": [],
    "notes": ""
  },
  "emails": [],
  "notes": "Source: linkedin | Posted: 2026-04-08 | Type: fulltime",
  "created_at": "2026-04-10T13:44:42.709010",
  "updated_at": "2026-04-10T13:44:42.709022",
  "status_history": []
}