{
  "id": "561eebb6",
  "title": "Vice President, Business Development",
  "company": "Precision Medicine Group",
  "url": "https://www.indeed.com/viewjob?jk=ee0200fe19ff0dc6",
  "source": "jobspy_indeed",
  "intake_source": "api",
  "raw_jd": "**Position Summary**\n\n\n\nThe **VP Business Development (BD)** for **Precision AQ (PAQ) Services and proprietary PAQ Products** is a high\\-impact, revenue\\-driving role focused on aggressively expanding PAQ's footprint within the life sciences sector. This position demands a proactive, results\\-oriented professional with exceptional business acumen and a relentless drive to win new business.\n\n\n\nThe ideal candidate thrives on identifying and pursuing high\\-value opportunities within small to midsize pharma \\& biotech, building strategic relationships with key decision\\-makers, and consistently opening doors to new accounts. Acting as a true sales hunter, this individual will prospect, qualify, and close new revenue streams by promoting the full suite of PAQ Agency, Consultancy/HEOR and proprietary PAQ Products through both point solution and cross selling efforts.\n\n\n\nIn addition to driving new client acquisition, the Director/VP will collaborate closely with internal subject matter experts (SMEs) to craft compelling solutions and accelerate deal progression. Success in this role requires a competitive mindset, strong negotiation skills, and the ability to convert opportunities into long\\-term partnerships.\n\n\n\nThis position reports to the PAQ SVP of Strategic Business Development\n\n\n**This position is accountable for:**\n\n\n* Developing and executing a strategic Territory Business Plan (codified annually) to drive new revenue and sales growth of all PAQ Agency, Consultancy/HEOR and proprietary PAQ Products in collaboration with identified SMEs and as measured by sales bookings \u2013 and directly accountable for a select group of prioritized accounts. This plan is considered the key playbook and is updated on a monthly basis to drive accountability and focus\n* Collaborating with PAQ Practice Areas to identify, coordinate and advance go to market motions (what and how we sell) and expand PAQ market share within targeted accounts\n* Building and maintaining relationships with clients (especially at the senior executive level), and leveraging these relationships to generate new business opportunities and drive revenue growth\n* Managing client opportunities from prospecting, solution development input with emphasis on tying back to voice of the customer and SOW finalization. Once successfully sold, transitioning the client to PAQ Service and/or Product Teams\n* Promoting PAQ capabilities and solutions through coordinated lead generation activities (e.g., conferences, trade shows, webinars, etc.) individually and in conjunction with PAQ's Marketing/Lead Generation Team\n* Providing competitive intelligence to broader Sales and Marketing Teams\n\n\n**Essential Business Development functions of the job include but are not limited to:**\n\n\n* Developing and executing on annual strategic Territory Business Plan on a monthly basis and during 1:1 sessions with manager to drive new revenue and sales growth of all PAQ Agency, Consultancy/HEOR and proprietary PAQ Products as measured by sales bookings\n* Create ongoing client\\-specific development strategies and plans to achieve annual business development and sales targets by client\n* Collaborate with PAQ Chief Business Office, Sale Operations and Practice Areas to inform budgets, forecasts, competitive intelligence and metrics\n* Building and maintaining relationships with clients (especially at the senior executive level), and leveraging these relationships to generate new business opportunities and drive revenue growth\n* Engage life science clients \u2013 either individually or in group presentations \u2013 to create and cultivate new relationships that lead to additional revenue opportunities\n* Managing client opportunities from prospecting, solution development, SOW finalization, and successful transition of client to PAQ Practice Area Teams\n* Actively manage the client sales cycle including prospecting, stakeholder meetings, proposal development, proposal delivery, pipeline management, and transition to implementation\n* Anticipate client needs and prepare executive summaries and presentations that cultivate opportunities and demonstrate the value of PAQ solutions\n* Negotiate client deliverables and development/maintenance of value\\-based pricing\n* Maintain and update client records in Salesforce in a timely manner\n* Collaborating with PAQ Practice Areas to coordinate and advance cross\\-selling opportunities and expand PAQ market share within prioritized accounts\n* Communicate client needs, feedback and recommendations with PAQ Practice Areas\n* Initiate PAQ\\-wide communications and collaboration to further the PAQ value and foothold within the client\n* Coordinate with PAQ Marketing and Sales Operations to inform strategic marketing and lead generation activities\n* Promoting PAQ capabilities and solutions through involvement in lead generation activities (e.g., conferences, trade shows, webinars, virtual meetings, etc.)\n* Represent existing engagement resources and innovation by presenting at conferences and trade shows\n* Expertly manage subsequent relationships as part of the selling process\n* Directing analysis to identify trends, competitive landscape and potential opportunities\n* Contribute to pricing and competitive positioning for PAQ Services and Products\n* Be a student of the life science marketing industry knowledgeable of new products, platforms, and Products\n* Spearhead competitive assessment by tracking competitors and their initiatives and analyzing competitive threats from within and outside the market\n* Travel up to 50%\n\n\n**Qualifications**\n\n\n* Required\n* BS in business and/or marketing, or similar\n* 10\\+ years of experience, optimally in life sciences company sales and marketing positions, or professional Products firms selling products and/or consultancy to life science companies\n* Successful track record in driving revenue growth, achieving business results\n* Expertise in consultative, insight\\-focused account\\-based selling approach\n* Comprehensive understanding of life science customer experience and engagement strategies and tactics\n* Demonstrated broad influence leading cross\\-functionally in organizations\n* Computer applications: MS Office applications\n* Preferred\n* MBA/MS in business and/or marketing, or similar\n* Computer applications: Salesforce.com\n\n\n**Skills**\n\n\n* Communication: Excellent communication and people skills, with the ability to articulate complex ideas and solutions in a clear and compelling manner.\n* Project Management \\& Collaboration: Strong project management skills, with the ability to manage multiple projects simultaneously and to work effectively with cross\\-functional teams.\n* Sales: Ability to identify, hunt, qualify, and negotiate effectively with clients to close business deals. Experience with consultative, insight\\-focused account\\-based selling approach\n* Analysis: Strong analytical skills and the ability to use data and metrics to drive decision\\-making and measure the success of business development efforts.\n\n\n**Competencies**\n\n\n* Strategic Thinking: Ability to think creatively and strategically, to identify and pursue new business opportunities, develop effective business plans, and achieve organizational goals.\n* Relationship\\-building: Ability to build and maintain strong relationships with clients (especially at the senior executive level), and to leverage these relationships to generate new business opportunities and drive revenue growth.\n* Industry Knowledge: Strong understanding of the consulting Products and life sciences industries, including market trends, competitive landscape, and emerging opportunities.\n* Adaptability: Ability to adapt to changing market conditions, client needs, and business priorities, and to pivot strategies and tactics as needed to achieve business goals.\n* Results\\-orientation: Track record of success in driving revenue growth, achieving business targets, and delivering results.\n\n\nAny data provided as a part of this application will be stored in accordance with our Privacy Policy. For CA applicants, please also refer to our CA Privacy Notice.\n\n\n\nPrecision Medicine Group is an Equal Opportunity Employer. Employment decisions are made without regard to race, color, age, religion, sex, sexual orientation, gender identity, national origin, disability, veteran status or other characteristics protected by law.\n\n\n\nIf you are an individual with a disability and require a reasonable accommodation to complete any part of the application process or are limited in the ability or unable to access or use this online application process and need an alternative method for applying, you may contact Precision Medicine Group at QuestionForHR@precisionmedicinegrp.com.\n\n\n\nIt has come to our attention that some individuals or organizations are reaching out to job seekers and posing as potential employers presenting enticing employment offers. We want to emphasize that these offers are not associated with our company and may be fraudulent in nature. Please note that our organization will not extend a job offer without prior communication with our recruiting team, hiring managers and a formal interview process.",
  "pay_range": "$170,000 - $255,000/year",
  "market_lane": "ignore",
  "status": "scored",
  "score": {
    "skills_match": 0,
    "scope_impact": 1,
    "pay_alignment": 0,
    "gut_interest": 0,
    "total": 1,
    "skills_rationale": "This is a business development/sales role focused on life sciences industry relationship building and revenue generation. The candidate's background is entirely in data analytics, BI architecture, and technical systems - completely different skill domains with zero overlap.",
    "scope_rationale": "The VP level scope matches candidate seniority, but this is a pure sales/BD leadership role requiring client relationship management and revenue generation. Candidate has technical leadership experience but no sales, business development, or life sciences industry background.",
    "pay_rationale": "No salary range provided in the job description, making pay alignment assessment impossible.",
    "keyword_gaps": [
      "business development",
      "sales",
      "life sciences",
      "pharma",
      "biotech",
      "client relationship management",
      "revenue generation",
      "consultative selling",
      "account management"
    ],
    "red_flags": [
      "Complete skill domain mismatch",
      "No relevant industry experience",
      "Role requires 50% travel"
    ],
    "bullshit_flag": false,
    "bullshit_reason": "",
    "recommended_resume": "none",
    "recommended_lane": "ignore",
    "raw_analysis": "This VP Business Development role in life sciences is completely misaligned with the candidate's technical background in data analytics and BI architecture. The role requires sales expertise, client relationship building, and life sciences industry knowledge - none of which appear in the candidate's profile. This represents a fundamental career pivot rather than a natural progression of existing skills."
  },
  "cover_letters": [],
  "tailored_resume": "",
  "tailored_resume_docx": "",
  "applied_at": "",
  "follow_up": {
    "due_at": "",
    "sent_at": "",
    "count": 0,
    "contact_email": "",
    "contact_name": "",
    "contact_phone": "",
    "extracted_emails": [],
    "extracted_links": [],
    "notes": ""
  },
  "emails": [],
  "notes": "Source: indeed | Posted: 2026-04-08 | Type: nan",
  "created_at": "2026-04-10T15:18:39.237316",
  "updated_at": "2026-04-10T15:18:48.934590",
  "status_history": [
    {
      "from": "new",
      "to": "scored",
      "at": "2026-04-10T15:18:48.934546"
    }
  ]
}